pypeblar/__init__.py
pypeblar/api_client.py
pypeblar/api_response.py
pypeblar/configuration.py
pypeblar/exceptions.py
pypeblar/py.typed
pypeblar/rest.py
pypeblar/api/__init__.py
pypeblar/api/ev_interface_api.py
pypeblar/api/health_api.py
pypeblar/api/meter_api.py
pypeblar/api/system_api.py
pypeblar/models/__init__.py
pypeblar/models/api_error.py
pypeblar/models/ev_interface_response.py
pypeblar/models/evinterface_patch_request.py
pypeblar/models/health_get200_response.py
pypeblar/models/meter_get200_response.py
pypeblar/models/system_get200_response.py
pypeblar-0.3.2.dist-info/LICENSE
pypeblar-0.3.2.dist-info/METADATA
pypeblar-0.3.2.dist-info/WHEEL
pypeblar-0.3.2.dist-info/top_level.txt
pypeblar-0.3.2.dist-info/RECORD
