Metadata-Version: 2.1
Name: pypeblar
Version: 0.3.2
Summary: Peblar local REST API
Home-page: 
Author: Peblar - Prodrive Technologies NE B.V.
Author-email: team@openapitools.org
Keywords: OpenAPI,OpenAPI-Generator,Peblar local REST API
License-File: LICENSE
Requires-Dist: urllib3 <3.0.0,>=1.25.3
Requires-Dist: python-dateutil
Requires-Dist: aiohttp >=3.0.0
Requires-Dist: pydantic <2,>=1.10.5
Requires-Dist: aenum
